odoo/addons/l10n_nl_cbs_export/README.rst
odoo/addons/l10n_nl_cbs_export/__init__.py
odoo/addons/l10n_nl_cbs_export/__manifest__.py
odoo/addons/l10n_nl_cbs_export/data/cbs_export_file_sequence.xml
odoo/addons/l10n_nl_cbs_export/data/cron_process_cbs_export.xml
odoo/addons/l10n_nl_cbs_export/doc/Codelijst_1Goederenstroom.pdf
odoo/addons/l10n_nl_cbs_export/doc/Codelijst_2Vervoerwijze.pdf
odoo/addons/l10n_nl_cbs_export/doc/Codelijst_4Statistisch Stelsel.pdf
odoo/addons/l10n_nl_cbs_export/doc/Codelijst_5Transactie.pdf
odoo/addons/l10n_nl_cbs_export/doc/RLO_2017_NL.pdf
odoo/addons/l10n_nl_cbs_export/doc/file-layout.xlsx
odoo/addons/l10n_nl_cbs_export/i18n/l10n_nl_cbs_export.pot
odoo/addons/l10n_nl_cbs_export/i18n/nl.po
odoo/addons/l10n_nl_cbs_export/i18n/nl_NL.po
odoo/addons/l10n_nl_cbs_export/models/__init__.py
odoo/addons/l10n_nl_cbs_export/models/account_invoice.py
odoo/addons/l10n_nl_cbs_export/models/cbs_export_file.py
odoo/addons/l10n_nl_cbs_export/readme/CONFIGURE.rst
odoo/addons/l10n_nl_cbs_export/readme/CONTRIBUTORS.rst
odoo/addons/l10n_nl_cbs_export/readme/CREDITS.rst
odoo/addons/l10n_nl_cbs_export/readme/DESCRIPTION.rst
odoo/addons/l10n_nl_cbs_export/readme/INSTALL.rst
odoo/addons/l10n_nl_cbs_export/readme/ROADMAP.rst
odoo/addons/l10n_nl_cbs_export/readme/USAGE.rst
odoo/addons/l10n_nl_cbs_export/security/cbs_export_file_security.xml
odoo/addons/l10n_nl_cbs_export/security/ir.model.access.csv
odoo/addons/l10n_nl_cbs_export/static/description/icon.png
odoo/addons/l10n_nl_cbs_export/static/description/index.html
odoo/addons/l10n_nl_cbs_export/tests/__init__.py
odoo/addons/l10n_nl_cbs_export/tests/test_cbs_export_file.py
odoo/addons/l10n_nl_cbs_export/view/cbs_export_file_view.xml
odoo11_addon_l10n_nl_cbs_export-11.0.1.0.1.dist-info/METADATA
odoo11_addon_l10n_nl_cbs_export-11.0.1.0.1.dist-info/RECORD
odoo11_addon_l10n_nl_cbs_export-11.0.1.0.1.dist-info/WHEEL
odoo11_addon_l10n_nl_cbs_export-11.0.1.0.1.dist-info/top_level.txt
